Kyros/ExecTime.py
Kyros/__init__.py
Kyros/__main__.py
Kyros/math.py
Kyros/printutils.py
Kyros/ThreeDeeify/__init__.py
Kyros/coloring/__init__.py
Kyros/videoify/__init__.py
Kyros-3.1.0.dist-info/LICENSE
Kyros-3.1.0.dist-info/METADATA
Kyros-3.1.0.dist-info/WHEEL
Kyros-3.1.0.dist-info/top_level.txt
Kyros-3.1.0.dist-info/RECORD
