Metadata-Version: 2.1
Name: Kyros
Version: 3.1.0
Summary: A Class Based Python Library for Fractal Generation
Author: @some1and2
Author-email: 04x0xx@gmail.com
License: GPL-3.0
License-File: LICENSE
Requires-Dist: Pillow ==9.1.0
Requires-Dist: numba ==0.57.1
Requires-Dist: opencv-python ==4.6.0.66
